ts_data_generator/__init__.py
ts_data_generator/cli.py
ts_data_generator/data_gen.py
ts_data_generator/utils.py
ts_data_generator/schema/__init__.py
ts_data_generator/schema/converter.py
ts_data_generator/schema/models.py
ts_data_generator/utils/__init__.py
ts_data_generator/utils/functions.py
ts_data_generator/utils/trends.py
ts_data_generator-0.2.6.dist-info/METADATA
ts_data_generator-0.2.6.dist-info/WHEEL
ts_data_generator-0.2.6.dist-info/entry_points.txt
ts_data_generator-0.2.6.dist-info/licenses/LICENSE
ts_data_generator-0.2.6.dist-info/RECORD
