Metadata-Version: 2.4
Name: ts-data-generator
Version: 0.2.6
Summary: A Python library for generating synthetic time series data
Project-URL: Repository, https://github.com/manojmanivannan/ts-data-generator.git
Author-email: Manoj Manivannan <manojm18@live.in>
License: MIT
License-File: LICENSE
Keywords: data generator,python,synthetic data,time series
Classifier: License :: OSI Approved :: MIT License
Classifier: Operating System :: OS Independent
Classifier: Programming Language :: Python :: 3
Requires-Python: >=3.8
Requires-Dist: click
Requires-Dist: matplotlib
Requires-Dist: pandas
Requires-Dist: pydantic
Requires-Dist: pytest
Requires-Dist: python-dotenv
Provides-Extra: dev
Requires-Dist: black; extra == 'dev'
Requires-Dist: flake8; extra == 'dev'
